LICENSE
README.md
pyproject.toml
armory/matrix/__init__.py
armory/matrix/matrix_generation.py
armory/matrix/range.py
armory/matrix/version.py
armory_matrix-24.6.1.dist-info/METADATA
armory_matrix-24.6.1.dist-info/WHEEL
armory_matrix-24.6.1.dist-info/licenses/LICENSE
armory_matrix-24.6.1.dist-info/RECORD
