Metadata-Version: 2.3
Name: armory-matrix
Version: 24.6.1
Summary: Armory Evaluation Matrix Library
Author-email: Two Six Technologies <armory@twosixtech.com>
License-Expression: MIT
License-File: LICENSE
Classifier: Development Status :: 4 - Beta
Classifier: License :: OSI Approved :: MIT License
Classifier: Programming Language :: Python :: 3
Classifier: Topic :: Scientific/Engineering :: Artificial Intelligence
Requires-Python: >=3.8
